setup.cfg
setup.py
tonto/__init__.py
tonto.egg-info/PKG-INFO
tonto.egg-info/SOURCES.txt
tonto.egg-info/dependency_links.txt
tonto.egg-info/top_level.txt