Metadata-Version: 2.1
Name: tonto
Version: 23.3.12.2
Summary: Tonto or nummy - Python advanced functionality module
Author: Igor_Shapovalov_Andrejovich
Author-email: igor.shapovalov.andrejovich@gmail.com
